README.md
setup.py
Microsoft/__init__.py
Microsoft/Finance/__init__.py
Microsoft/Finance/Common/DataBricks.py
Microsoft/Finance/Common/Spark.py
Microsoft/Finance/Common/Utilities.py
Microsoft/Finance/Common/__init__.py
Microsoft/Finance/DataStandards/__init__.py
Microsoft/Finance/DataStandards/UnitTest/__init__.py
Microsoft/Finance/DataStandards/UnitTest/TestCase/BridgeTestCase.py
Microsoft/Finance/DataStandards/UnitTest/TestCase/CommonTestCase.py
Microsoft/Finance/DataStandards/UnitTest/TestCase/DimensionTestCase.py
Microsoft/Finance/DataStandards/UnitTest/TestCase/FactTestCase.py
Microsoft/Finance/DataStandards/UnitTest/TestCase/__init__.py
Microsoft/Finance/DataStandards/UnitTest/TestSuite/BaseTestSuite.py
Microsoft/Finance/DataStandards/UnitTest/TestSuite/BridgeTestSuite.py
Microsoft/Finance/DataStandards/UnitTest/TestSuite/DimensionTestSuite.py
Microsoft/Finance/DataStandards/UnitTest/TestSuite/FactTestSuite.py
Microsoft/Finance/DataStandards/UnitTest/TestSuite/StagingTestSuite.py
Microsoft/Finance/DataStandards/UnitTest/TestSuite/__init__.py
Microsoft/Finance/DataStandards/Utilities/DeploymentMatrix.py
Microsoft/Finance/DataStandards/Utilities/TestEvent.py
Microsoft/Finance/DataStandards/Utilities/TestObject.py
Microsoft/Finance/DataStandards/Utilities/TestUtilities.py
Microsoft/Finance/DataStandards/Utilities/__init__.py
msftfdnepy.egg-info/PKG-INFO
msftfdnepy.egg-info/SOURCES.txt
msftfdnepy.egg-info/dependency_links.txt
msftfdnepy.egg-info/not-zip-safe
msftfdnepy.egg-info/requires.txt
msftfdnepy.egg-info/top_level.txt