Metadata-Version: 2.1
Name: msftfdnepy
Version: 0.3.5
Summary: data testing and processing tools
Home-page: https://microsoft.com
Author: Phil Bennett
Author-email: phbennet@microsoft.com
License: UNKNOWN
Platform: UNKNOWN
Requires-Python: >=3.0
